setup.py
ageng_distributions.egg-info/PKG-INFO
ageng_distributions.egg-info/SOURCES.txt
ageng_distributions.egg-info/dependency_links.txt
ageng_distributions.egg-info/not-zip-safe
ageng_distributions.egg-info/top_level.txt
distributions/Binomialdistribution.py
distributions/Gaussiandistribution.py
distributions/Generaldistribution.py
distributions/__init__.py