Metadata-Version: 1.0
Name: ageng-distributions
Version: 0.2
Summary: Gaussian distributions from udacity
Home-page: UNKNOWN
Author: Widya Ageng
Author-email: ageng.setyatutuko@gmail.com
License: UNKNOWN
Platform: UNKNOWN
